setup.py
sumrnaseq/__init__.py
sumrnaseq.main.egg-info/PKG-INFO
sumrnaseq.main.egg-info/SOURCES.txt
sumrnaseq.main.egg-info/dependency_links.txt
sumrnaseq.main.egg-info/entry_points.txt
sumrnaseq.main.egg-info/namespace_packages.txt
sumrnaseq.main.egg-info/not-zip-safe
sumrnaseq.main.egg-info/requires.txt
sumrnaseq.main.egg-info/top_level.txt
sumrnaseq/main/__init__.py
sumrnaseq/main/command_line.py
sumrnaseq/main/main.py