Metadata-Version: 1.1
Name: sumrnaseq.main
Version: 0.1.0
Summary: main program
Home-page: UNKNOWN
Author: Zhi Zhang
Author-email: zhi.zhang@uni.lu
License: GPL
Keywords: main
Platform: UNKNOWN
Classifier: Framework :: Plone
Classifier: Framework :: Zope2
Classifier: Framework :: Zope3
Classifier: Programming Language :: Python
Classifier: Topic :: Software Development :: Libraries :: Python Modules
